{"entries":{"https://www.riverbankcomputing.com/static/Docs/PyQt6/sip-classes.html":{"timestamp":{"secs_since_epoch":1647499798,"nanos_since_epoch":786841000},"valid":true},"https://github.com/rferrazz/pyqt4topyqt5":{"timestamp":{"secs_since_epoch":1647499798,"nanos_since_epoch":8135000},"valid":true},"https://github.com/ankitects/anki/blob/master/pylib/tools/genhooks.py":{"timestamp":{"secs_since_epoch":1647499798,"nanos_since_epoch":214477000},"valid":true},"https://docs.ankiweb.net/misc.html#debug-console":{"timestamp":{"secs_since_epoch":1647499797,"nanos_since_epoch":538791000},"valid":true},"https://www.jetbrains.com/pycharm/":{"timestamp":{"secs_since_epoch":1647499797,"nanos_since_epoch":547264000},"valid":true},"http://docs.python.org/tutorial/":{"timestamp":{"secs_since_epoch":1647499797,"nanos_since_epoch":566263000},"valid":true},"https://ankiweb.net/shared/addons/":{"timestamp":{"secs_since_epoch":1647499798,"nanos_since_epoch":809169000},"valid":true},"https://download.qt.io/":{"timestamp":{"secs_since_epoch":1647499798,"nanos_since_epoch":945110000},"valid":true},"https://github.com/ankitects/anki-addons/blob/master/demos/":{"timestamp":{"secs_since_epoch":1647499798,"nanos_since_epoch":368721000},"valid":true},"http://pyqt.sourceforge.net/Docs/PyQt4/new_style_signals_slots.html":{"timestamp":{"secs_since_epoch":1647499798,"nanos_since_epoch":954123000},"valid":true},"https://github.com/ankitects/anki/blob/main/docs/architecture.md":{"timestamp":{"secs_since_epoch":1647499797,"nanos_since_epoch":987139000},"valid":true},"https://github.com/ankitects/anki/blob/master/qt/tools/genhooks_gui.py":{"timestamp":{"secs_since_epoch":1647499798,"nanos_since_epoch":262954000},"valid":true}}}